riboraptor/__init__.py
riboraptor/cli.py
riboraptor/coherence.py
riboraptor/count.py
riboraptor/dtw.py
riboraptor/fasta.py
riboraptor/genome.py
riboraptor/helpers.py
riboraptor/normalization.py
riboraptor/plotting.py
riboraptor/statistics.py
riboraptor/utils.py
riboraptor/wig.py
riboraptor/annotation/hg38/cds.bed.gz
riboraptor/annotation/hg38/genes.bed.gz
riboraptor/annotation/hg38/hg38.chrom.sizes
riboraptor/annotation/hg38/start_codon.bed.gz
riboraptor/annotation/hg38/stop_codon.bed.gz
riboraptor/annotation/hg38/utr3.bed.gz
riboraptor/annotation/hg38/utr5.bed.gz
riboraptor/annotation/mm10/cds.bed.gz
riboraptor/annotation/mm10/genes.bed.gz
riboraptor/annotation/mm10/mm10.chrom.sizes
riboraptor/annotation/mm10/start_codon.bed.gz
riboraptor/annotation/mm10/stop_codon.bed.gz
riboraptor/annotation/mm10/utr3.bed.gz
riboraptor/annotation/mm10/utr5.bed.gz
riboraptor/annotation/notebooks/gencode-regions-human.ipynb
riboraptor/annotation/notebooks/gencode-regions-mouse.ipynb
riboraptor-0.2.2.dist-info/METADATA
riboraptor-0.2.2.dist-info/RECORD
riboraptor-0.2.2.dist-info/WHEEL
riboraptor-0.2.2.dist-info/entry_points.txt
riboraptor-0.2.2.dist-info/top_level.txt
