Metadata-Version: 2.1
Name: riboraptor
Version: 0.2.2
Summary: Python package to analyse ribosome profiling data
Home-page: https://github.com/saketkc/riboraptor
Author: Saket Choudhary
Author-email: saketkc@gmail.com
License: BSD license
Keywords: riboraptor
Platform: UNKNOWN
Classifier: License :: OSI Approved :: BSD License
Classifier: Natural Language :: English
Classifier: Programming Language :: Python :: 2
Classifier: Programming Language :: Python :: 2.7
Classifier: Programming Language :: Python :: 3
Classifier: Programming Language :: Python :: 3.5
Requires-Dist: matplotlib (>=2.1.0)
Requires-Dist: numpy (>=1.11.0)
Requires-Dist: pandas (>=0.20.3)
Requires-Dist: pybedtools (>=0.7.10)
Requires-Dist: pyBigWig (>=0.2.8)
Requires-Dist: pyfaidx (>=0.5.0)
Requires-Dist: pysam (>=0.11.2.2)
Requires-Dist: scipy (>=0.19.1)
Requires-Dist: seaborn (>=0.8.1)
Requires-Dist: statsmodels (>=0.8.0)
Requires-Dist: six (>=1.11.0)
Requires-Dist: Click (>=6.0)
Requires-Dist: click-help-colors (>=0.3)
Requires-Dist: HTSeq (>=0.9.1)
Requires-Dist: Biopython (>=1.70)
